LICENSE
README.md
pyproject.toml
setup.cfg
setup.py
kornet/__init__.py
kornet/__main__.py
kornet.egg-info/PKG-INFO
kornet.egg-info/SOURCES.txt
kornet.egg-info/dependency_links.txt
kornet.egg-info/entry_points.txt
kornet.egg-info/requires.txt
kornet.egg-info/top_level.txt
kornet/fleet/__init__.py
kornet/fleet/models.py
kornet/fleet/raw/__init__.py
kornet/fleet/raw/hosts_parser.py
kornet/fleet/raw/models.py
kornet/shared/__init__.py
kornet/shared/models.py
kornet/strategy/__init__.py
kornet/strategy/models.py
kornet/strategy/services.py
kornet/strategy/adapters/__init__.py
kornet/strategy/adapters/abstract.py
kornet/strategy/adapters/asyncssh_comm.py
kornet/strategy/adapters/paramiko_ssh_comm.py
kornet/strategy/machines/__init__.py
kornet/strategy/machines/models.py
kornet/strategy/orders/__init__.py
kornet/strategy/orders/handlers.py
kornet/strategy/orders/models.py
kornet/strategy/orders/orders.py
kornet/strategy/orders/recon/__init__.py
kornet/strategy/orders/recon/catalog.py
kornet/strategy/orders/recon/enum.py
kornet/strategy/orders/recon/handlers.py
kornet/strategy/orders/recon/models.py
kornet/strategy/orders/recon/orders.py
kornet/strategy/raw/__init__.py
kornet/strategy/raw/models.py
kornet/strategy/raw/strategy_parser.py